{"ocr_results":[{"text":"1542","box":[[92,167],[152,167],[152,198],[92,198]]},{"text":"毛泽东传","box":[[567,165],[682,165],[682,197],[567,197]]},{"text":"法律，不参加居留国国内的非法活动，搞好同居留国政府和人民","box":[[83,254],[1164,251],[1164,282],[83,285]]},{"text":"的关系。他又特别说道：“国籍问题也要搞清楚，到底是中国籍","box":[[84,313],[1165,311],[1165,342],[84,344]]},{"text":"还是外国籍，不应该有双重国籍。”","box":[[80,372],[662,367],[662,404],[81,409]]},{"text":"毛泽东的明确承诺，使缅甸来宾喜出望外。吴努说：“在周","box":[[160,433],[1165,430],[1165,460],[160,463]]},{"text":"总理访问仰光的时候，我曾经向他提出这个问题。他说这个问题","box":[[85,492],[1166,489],[1166,521],[86,524]]},{"text":"超出他的权限，必须回国后同他的同事们商量。今天听到主席关","box":[[84,552],[1167,550],[1167,581],[84,583]]},{"text":"于双重国籍所说的话，非常高兴。’","box":[[84,610],[659,604],[659,642],[85,648]]},{"text":"中国政府非常希望在和平共处五项原则的基础上，同泰国结","box":[[167,669],[1169,669],[1169,699],[167,699]]},{"text":"成友好关系。这个意愿，毛泽东曾向尼赫鲁表达过了，这次又向","box":[[89,729],[1168,729],[1168,759],[89,759]]},{"text":"吴努提出，希望他从中给予帮助。吴努痛快地答应了，说他和尼","box":[[89,787],[1169,787],[1169,817],[89,817]]},{"text":"赫鲁总理将会把上述意见转达给泰国政府。","box":[[89,847],[800,848],[799,876],[88,875]]},{"text":"毛泽东和吴努还谈到亚非会议。毛泽东主动表示：“对于","box":[[166,904],[1171,905],[1171,939],[166,938]]},{"text":"亚非会议，我们很感兴趣。尼赫鲁总理告诉我们，亚非会议的","box":[[89,965],[1171,967],[1171,997],[88,995]]},{"text":"宗旨是扩大和平区域和反对殖民主义。我们认为，这个宗旨很","box":[[89,1026],[1170,1026],[1170,1056],[89,1056]]},{"text":"好，我们支持这个会议。如果各国同意，我们希望参加这个会","box":[[87,1083],[1170,1084],[1170,1116],[87,1114]]},{"text":"议。”","box":[[84,1136],[183,1136],[183,1180],[84,1180]]},{"text":"吴努告诉毛泽东，有些国家会建议蒋介石参加会议。毛泽东","box":[[165,1202],[1170,1203],[1170,1234],[165,1233]]},{"text":"说：“看来似乎有些困难啊！不过我们还是希望中国能够被邀","box":[[89,1260],[1173,1260],[1173,1293],[89,1293]]},{"text":"请。只是不能像有些人建议的那样，请中国参加联合国，又把蒋","box":[[88,1319],[1172,1322],[1172,1355],[87,1353]]},{"text":"介石保留在联合国里。这样我们就不好去了。因为台湾问题是中","box":[[89,1382],[1170,1382],[1170,1412],[89,1412]]},{"text":"国的内政，台湾是中国的一部分。”毛泽东再次表示：“如果我","box":[[91,1440],[1172,1441],[1172,1472],[90,1471]]},{"text":"们能够参加亚非会议，我们将感到光荣。”①","box":[[87,1497],[818,1495],[818,1533],[88,1535]]},{"text":"正如吴努估计的那样，在这年十二月二十八日和二十九日","box":[[167,1559],[1168,1560],[1168,1591],[167,1590]]},{"text":"召开的科伦坡五国茂物会议上，是否邀请中华人民共和国参加","box":[[91,1618],[1172,1619],[1172,1649],[90,1648]]},{"text":"①毛泽东同吴努第一次会谈记录，1954年12月1日。毛泽东的谈话内容，见","box":[[145,1737],[1172,1740],[1172,1768],[145,1765]]},{"text":"《毛泽东外交文选》，中央文献出版社、世界知识出版社1994年12月版，第177一186","box":[[89,1781],[1174,1782],[1174,1809],[88,1808]]},{"text":"页。","box":[[88,1825],[132,1825],[132,1853],[88,1853]]}],"dimensions":{"height":2026,"width":1241}}