{"ocr_results":[{"text":"五十五、创造一个和平的国际环境","box":[[387,188],[818,188],[818,212],[387,212]]},{"text":"1559","box":[[1076,185],[1137,185],[1137,215],[1076,215]]},{"text":"平共处五项原则，签订协议，解决了华侨的双重国籍这个中国同","box":[[62,275],[1146,275],[1146,305],[62,305]]},{"text":"一些邻国间存在的敏感问题，印尼政府大为赞赏。","box":[[60,330],[894,333],[894,364],[60,361]]},{"text":"同年五月二十五日至六月七日，印尼总理沙斯特罗阿米佐约","box":[[138,390],[1144,391],[1144,423],[138,421]]},{"text":"访问中国，中国政府隆重接待。","box":[[62,450],[584,450],[584,480],[62,480]]},{"text":"五月二十六日，毛泽东会见了沙斯特罗阿米佐约。朱德、刘","box":[[138,506],[1146,507],[1146,538],[138,537]]},{"text":"少奇、周恩来、邓小平、陈毅等参加会见。","box":[[61,564],[772,564],[772,598],[61,598]]},{"text":"毛泽东以充满热情的语言表达了对客人的欢迎：“欢迎你","box":[[139,624],[1147,624],[1147,654],[139,654]]},{"text":"们，欢迎其他各位朋友，我们十分欢迎你们。我们是朋友，我们","box":[[61,681],[1147,682],[1147,713],[61,712]]},{"text":"和中国人民都很高兴看到你们。”","box":[[63,739],[601,738],[601,770],[63,771]]},{"text":"讲到亚非会议，毛泽东十分称赞印尼对这次会议所做的","box":[[138,798],[1146,799],[1146,830],[138,829]]},{"text":"贡献。他说：亚非国家的团结是有希望的，万隆会议已经走了","box":[[63,856],[1144,857],[1144,888],[63,887]]},{"text":"第一步。在西方国家面前，我们的问题是团结起来，保卫自己，","box":[[61,913],[1144,915],[1144,947],[61,945]]},{"text":"而不是互相打主意，彼此损害。为此，就要采取步骤来消除存","box":[[63,974],[1147,974],[1147,1004],[63,1004]]},{"text":"在于我们之间的不了解和障碍，增加互相的了解。他说，过去","box":[[61,1030],[1148,1030],[1148,1063],[61,1063]]},{"text":"中印间存在的西藏问题，中缅间有华侨和国界问题，中国和","box":[[63,1088],[1148,1089],[1148,1121],[63,1120]]},{"text":"印尼也有华侨问题，这些都能够友好地解决。毛泽东再一次表达","box":[[63,1147],[1147,1148],[1147,1179],[63,1178]]},{"text":"了中国对改善同泰国、菲律宾关系的愿望，希望印尼总理见到","box":[[64,1205],[1147,1206],[1147,1237],[64,1236]]},{"text":"泰国、菲律宾的领导人时，告诉他们中国是想和他们的国家友好","box":[[62,1263],[1147,1264],[1147,1296],[62,1295]]},{"text":"相处的。","box":[[62,1322],[196,1322],[196,1354],[62,1354]]},{"text":"沙斯特罗阿米佐约此行的一个重要目的，是想促成中美两国","box":[[139,1380],[1146,1382],[1145,1412],[139,1410]]},{"text":"就台湾海峡局势举行谈判。毛泽东表示：“我们愿意用和平的方","box":[[63,1437],[1147,1439],[1147,1470],[63,1469]]},{"text":"法来解决存在的问题。打仗总是不好的”。他以两次世界大战的","box":[[62,1496],[1147,1497],[1147,1528],[62,1527]]},{"text":"历史为例证，说明战争的政治后果对西方国家并不利。他说：","box":[[64,1556],[1147,1556],[1147,1586],[64,1586]]},{"text":"“正是考虑了这一点，我们说，用谈判来解决问题，试试看。况","box":[[61,1612],[1148,1614],[1147,1647],[61,1645]]},{"text":"且朝鲜战争和印度支那战争最后都是用谈判解决的，台湾问题也","box":[[65,1672],[1147,1673],[1147,1703],[65,1702]]},{"text":"可以用谈判解决。我们已经在万隆会议表明了这一点，可以用这","box":[[65,1729],[1147,1730],[1147,1761],[65,1760]]},{"text":"一点去说服西方国家。”他进一步提出：“如果美国愿意签订一","box":[[64,1786],[1147,1787],[1147,1821],[64,1820]]},{"text":"个和平条约，多长的时期都可以，五十年不够就一百年，不知道","box":[[64,1847],[1147,1847],[1147,1877],[64,1877]]}],"dimensions":{"height":2028,"width":1241}}