{"ocr_results":[{"text":"五十六、《关于正确处理人民内部矛盾的问题》和整风反右（上）","box":[[213,170],[1004,170],[1004,197],[213,197]]},{"text":"1619","box":[[1085,170],[1145,170],[1145,200],[1085,200]]},{"text":"识分子像惊弓之鸟，怕得厉害，他们要看一看，他们是一定要看","box":[[68,257],[1152,257],[1152,290],[68,290]]},{"text":"的，可能看上一二十年，二十年以后也还是要看的。我们党内同","box":[[69,315],[1153,315],[1153,348],[69,348]]},{"text":"志也是要看一看的。如“治病救人”一条，过去一些犯错误的","box":[[67,373],[1152,372],[1153,406],[67,407]]},{"text":"同志也是不相信，经过七大到八大，做了许多具体工作才相信。","box":[[70,435],[1149,435],[1149,465],[70,465]]},{"text":"“三反”反出那么多“老虎”，后来百分之八十都降下来了，一","box":[[65,489],[1150,491],[1149,524],[65,522]]},{"text":"百元以下的就不算贪污了，太多了嘛。一个人搞百把块钱，一世","box":[[70,548],[1154,548],[1154,581],[70,581]]},{"text":"就完了。“五反”开始也到处是坏人，后来五类一分，打击面就","box":[[69,608],[1154,608],[1154,638],[69,638]]},{"text":"小了。总之，共产党的政策要让大家来考验，领导者也要受被领","box":[[70,666],[1155,666],[1155,696],[70,696]]},{"text":"导者考验。","box":[[69,723],[242,723],[242,758],[69,758]]},{"text":"石西民：党内有一些干部说，现在搞百家争鸣不是时候。有","box":[[146,783],[1153,782],[1154,813],[146,814]]},{"text":"的认为百家争鸣与于百倍地加强政治思想工作相矛盾，重大政策","box":[[72,843],[1153,841],[1154,868],[72,870]]},{"text":"的传达要求先党内后党外，一下推开感到难办。","box":[[73,899],[902,899],[902,930],[73,930]]},{"text":"毛泽东：八大已做了结论，大规模阶级斗争已经基本结束，","box":[[142,958],[1154,956],[1155,986],[142,988]]},{"text":"提出“百花齐放、百家争鸣”正是时候。党与非党之间有堵墙，","box":[[71,1015],[1154,1014],[1154,1045],[71,1046]]},{"text":"墙不拆，如何争取群众？什么叫政治思想工作？政治思想工作是","box":[[71,1072],[1156,1071],[1156,1103],[71,1104]]},{"text":"为了争取群众嘛。不考虑争取群众，谈不上政治思想工作。现在","box":[[72,1132],[1156,1129],[1157,1160],[72,1163]]},{"text":"党与非党之间有条沟，而且很深。我并不是说党与非党不要有界","box":[[72,1190],[1156,1188],[1156,1219],[72,1221]]},{"text":"限，应该有条线，混起来不好，但是不应该变成鸿沟，脱离群","box":[[73,1248],[1157,1246],[1157,1278],[73,1280]]},{"text":"众。党内党外一起来好，这样快，就把许多人推上政治斗争舞","box":[[73,1307],[1158,1305],[1158,1336],[73,1338]]},{"text":"台，不然两三年也不得解决。现在党外传达很快，党内反而迟，","box":[[74,1365],[1156,1363],[1156,1394],[74,1396]]},{"text":"报上也很少反映。回去就要批评《人民日报》，是什么人的报纸？","box":[[73,1423],[1141,1421],[1141,1452],[73,1454]]},{"text":"石西民：有人提出报上开展百家争鸣要有五个条件：必须","box":[[150,1481],[1159,1479],[1159,1509],[150,1511]]},{"text":"有领导，有选择，有准备，有说服力，有利。有人不同意这种","box":[[73,1539],[1159,1537],[1159,1567],[73,1569]]},{"text":"说法。","box":[[72,1594],[193,1598],[192,1634],[71,1630]]},{"text":"毛泽东：这么多条件，叫我也难办。领导要有，搞方向就叫","box":[[153,1657],[1159,1654],[1159,1684],[153,1687]]},{"text":"领导了，但不要干涉过多。有领导是肯定的，但毛病一点不出，","box":[[78,1715],[1160,1711],[1160,1742],[78,1746]]},{"text":"难。有选择，也会选错的，准备它有错。有准备是对的，也不能","box":[[77,1774],[1162,1769],[1162,1801],[77,1805]]},{"text":"准备得那样周到。有说服力很对，这条比较具体。有利，看怎样","box":[[78,1831],[1162,1827],[1162,1858],[78,1862]]}],"dimensions":{"height":2028,"width":1241}}