{"ocr_results":[{"text":"1732","box":[[87,167],[146,167],[146,198],[87,198]]},{"text":"毛泽东传","box":[[561,166],[675,166],[675,198],[561,198]]},{"text":"负责人参加的中央工作会议，这就是著名的南宁会议。","box":[[76,254],[981,253],[981,286],[76,287]]},{"text":"在南宁会议前，有一个杭州会议，由华东六省市党委第一书","box":[[154,314],[1157,313],[1157,344],[154,345]]},{"text":"记参加。杭州会议共开了两次。一次是一九五七年十二月十六日","box":[[78,374],[1154,374],[1154,404],[78,404]]},{"text":"至十八日三天；一次是一九五八年一月三日、四日两天，这一次","box":[[79,431],[1158,430],[1158,461],[79,462]]},{"text":"有周恩来参加。据毛泽东说，第一次无结果而散，没有议出什么","box":[[77,488],[1156,487],[1156,519],[77,520]]},{"text":"名堂，第二次才积累一点意见。①","box":[[76,546],[627,543],[628,577],[76,580]]},{"text":"在一月三日和四日的会议上，毛泽东两次讲话，着重讲了领","box":[[154,604],[1160,603],[1160,633],[154,634]]},{"text":"导经济建设的方法问题，政治与业务的关系问题，敌我与人民内","box":[[80,663],[1157,663],[1157,693],[80,693]]},{"text":"部两类矛盾的问题，以及不断革命、技术革命等。并再次批评反","box":[[80,722],[1157,722],[1157,752],[80,752]]},{"text":"冒进，还第一次点名批评了周恩来等人。","box":[[82,780],[749,780],[749,810],[82,810]]},{"text":"杭州会议，实际上是南宁会议的序幕。毛泽东的两次讲话，","box":[[155,839],[1159,837],[1159,867],[155,869]]},{"text":"一共谈了十七个问题，可以说是《工作方法六十条》的形。","box":[[80,895],[1107,895],[1107,926],[80,926]]},{"text":"杭州会议一结束，毛泽东就离开杭州，乘专机经长沙，于一","box":[[154,954],[1157,952],[1157,983],[154,985]]},{"text":"月六日来到南宁。这里的气候依然温暖如春，江山如画，洋槐树","box":[[80,1011],[1159,1010],[1159,1040],[80,1041]]},{"text":"只有少数的黄吐子，告诉人们这里是秋天不是春天。毛泽东准备","box":[[81,1068],[1159,1067],[1159,1098],[81,1099]]},{"text":"在这里召开范围更大一点的中央工作会议。","box":[[81,1128],[791,1128],[791,1158],[81,1158]]},{"text":"他亲自写了一个会议通知，要求参加这次会议的，除刘少","box":[[157,1185],[1160,1183],[1160,1216],[157,1218]]},{"text":"奇、周恩来、陈云、邓小平、彭真及分管计划、财政、经济的几","box":[[80,1244],[1160,1243],[1160,1274],[80,1275]]},{"text":"位副总理李富春、李先念、薄一波外，还有国家技术委员会主","box":[[82,1303],[1161,1303],[1161,1334],[82,1334]]},{"text":"任、第一机械工业部部长黄敬，国家建设委员会主任、治金工业","box":[[81,1361],[1161,1361],[1161,1391],[81,1391]]},{"text":"部部长王鹤寿，新华通讯社社长、《人民日报》总编辑吴冷西。","box":[[81,1418],[1160,1418],[1160,1448],[81,1448]]},{"text":"要求参加会议的还有一些省市的负责人，包括黑龙江、陕西、四","box":[[80,1475],[1162,1474],[1162,1505],[80,1506]]},{"text":"川、河南、湖北、江西、湖南、广东、广西九省的省委第一书记","box":[[80,1534],[1162,1533],[1162,1564],[80,1565]]},{"text":"欧阳钦、张德生、李井泉、潘复生、王任重、杨尚奎、周小舟、","box":[[80,1591],[1166,1590],[1166,1624],[80,1625]]},{"text":"陶铸、刘建勋，以及北京市委第二书记刘仁、河南省委书记处书","box":[[82,1651],[1164,1650],[1164,1681],[82,1682]]},{"text":"记史向生、广西省委书记处书记韦国清，以及中央政治局的三位","box":[[80,1710],[1164,1708],[1164,1739],[80,1741]]},{"text":"D","box":[[138,1832],[172,1832],[172,1856],[138,1856]]},{"text":"毛泽东在中共中央政治局扩大会议上的讲话记录，1958年2月18日。","box":[[191,1831],[1069,1829],[1069,1855],[191,1857]]}],"dimensions":{"height":2026,"width":1241}}