{"ocr_results":[{"text":"六十一、炮击金门","box":[[483,166],[709,166],[709,196],[483,196]]},{"text":"1843","box":[[1072,165],[1132,165],[1132,196],[1072,196]]},{"text":"牌，中国政府坚决反对，蒋介石也不接受。至于第三张牌，由于","box":[[55,253],[1142,250],[1142,285],[55,287]]},{"text":"蒋介石的强烈不满，美国人还不会马上打出来。中央原先的方","box":[[54,312],[1140,311],[1140,342],[54,343]]},{"text":"针是准备分两步走：先收复包括金门、马祖在内的沿海岛屿，再","box":[[56,370],[1143,368],[1143,399],[56,401]]},{"text":"争取解放台湾。现根据目前的局势变化，决定还是把蒋介石继续","box":[[57,430],[1142,428],[1142,458],[57,460]]},{"text":"留在金门、马祖沿海岛屿上，暂时不收回，今后争取一下子收回","box":[[58,488],[1142,486],[1142,516],[58,518]]},{"text":"这些沿海岛屿、澎湖列岛和台湾。①","box":[[55,545],[647,540],[647,577],[55,583]]},{"text":"从“两步走”改变为“一揽子”解决，这是对台湾海峡关","box":[[133,604],[1143,601],[1144,634],[133,637]]},{"text":"系产生长远影响的重大决策。","box":[[60,664],[536,663],[536,694],[60,695]]},{"text":"后来，毛泽东在回顾炮打金门这段历史时，对于这个重大决","box":[[135,721],[1144,719],[1144,750],[135,752]]},{"text":"策是怎样改变的和为什么要改变，作了很详细很生动的说明：","box":[[59,779],[1087,778],[1087,808],[59,809]]},{"text":"“金门打炮每一个环节都是我跟总理搞的，如何打","box":[[214,836],[1066,836],[1066,870],[214,870]]},{"text":"法等等。那么一个严重的局面，美国十二艘航空母舰来","box":[[137,894],[1064,894],[1064,927],[137,927]]},{"text":"了六艘，第七舰队是他最大的舰队，搞边缘政策，护","box":[[140,956],[1065,956],[1065,986],[140,986]]},{"text":"航。这个地方是美国军舰，这个地方是国民党军舰","box":[[137,1013],[1067,1012],[1067,1043],[137,1044]]},{"text":"（主席讲这两句话时，摆两个茶杯作比一—记录者注）","box":[[138,1068],[1065,1068],[1065,1103],[138,1103]]},{"text":"相隔这么一点。他这里铺起美国国旗也不动，他也不打","box":[[139,1131],[1065,1130],[1065,1158],[139,1159]]},{"text":"我们，我们也不打他，我们专打国民党。这个事情不能","box":[[138,1187],[1066,1185],[1066,1216],[138,1218]]},{"text":"粗枝大叶，要很准确，很有纪律，后头转到双日不打单","box":[[138,1245],[1066,1244],[1066,1276],[138,1277]]},{"text":"日打，以后又搞什么告台湾同胞书这套东西。每天全世","box":[[143,1303],[1069,1303],[1069,1336],[143,1336]]},{"text":"界的一切舆论，一切消息，你都要看完，每天两大本","box":[[138,1362],[1068,1360],[1068,1393],[138,1395]]},{"text":"（指新华社编的内部资料《参考资料》一—引者注），","box":[[136,1418],[1072,1417],[1072,1455],[136,1456]]},{"text":"你才了解情况，才知道动向，不然怎么决策？开头我们","box":[[140,1481],[1071,1479],[1071,1510],[140,1512]]},{"text":"不是在这里报告了吗？那个时候，我们跟张文白，还有","box":[[141,1538],[1068,1537],[1068,1568],[141,1569]]},{"text":"许多朋友，都是一致的，要把金门、马祖搞回来。后头","box":[[139,1597],[1067,1595],[1067,1626],[139,1628]]},{"text":"一到武昌，我不是跟你（指张治中一—记录者注）一","box":[[139,1652],[1070,1654],[1070,1688],[139,1686]]},{"text":"道吗？形势不对了，金门、马祖还是留给蒋委员长比较","box":[[139,1712],[1069,1711],[1069,1742],[139,1743]]},{"text":"①","box":[[119,1834],[147,1834],[147,1860],[119,1860]]},{"text":"见周恩来同安东诺夫谈话记录，1958年10月5日。","box":[[176,1833],[817,1833],[817,1860],[176,1860]]}],"dimensions":{"height":2028,"width":1241}}